codefusion/__init__.py
codefusion/__main__.py
codefusion/_version.py
codefusion/default_config.toml
codefusion/cache/__init__.py
codefusion/cache/manager.py
codefusion/config/__init__.py
codefusion/config/loader.py
codefusion/core/__init__.py
codefusion/core/app.py
codefusion/core/detector.py
codefusion/core/filter.py
codefusion/core/grouper.py
codefusion/core/reader.py
codefusion/core/scanner.py
codefusion/core/security.py
codefusion/core/writer.py
codefusion/ignore/__init__.py
codefusion/ignore/manager.py
codefusion/plugins/__init__.py
codefusion/plugins/hooks.py
codefusion/plugins/loader.py
codefusion/plugins/builtin/__init__.py
codefusion/templates/__init__.py
codefusion/templates/base.py
codefusion/templates/default.py
codefusion/templates/html.py
codefusion/templates/markdown.py
codefusion/templates/renderer.py
codefusion/ui/__init__.py
codefusion/ui/cli.py
codefusion/ui/interactive.py
codefusion/ui/preview.py
codefusion/ui/wizard.py
codefusion/utils/__init__.py
codefusion/utils/constants.py
codefusion/utils/helpers.py
codefusion/utils/logging.py
codefusion-1.1.1.dist-info/METADATA
codefusion-1.1.1.dist-info/WHEEL
codefusion-1.1.1.dist-info/entry_points.txt
codefusion-1.1.1.dist-info/top_level.txt
codefusion-1.1.1.dist-info/RECORD
